<mvc:View xmlns:cards="sap.f.cards" xmlns:f="sap.f" xmlns:core="sap.ui.core" xmlns:layout="sap.ui.layout"
    controllerName="actions.controller.Master"
    xmlns:mvc="sap.ui.core.mvc"
    displayBlock="true"
    xmlns="sap.m"
>
	<Shell id="shell">
		<App id="app">
			<pages>
				<Page id="page" title="{i18n>title}">
					<layout:Splitter  width="100%">
						<Button width="100%" text="hello world" >
							<layoutData>
								<layout:SplitterLayoutData size="auto" resizable="false"/>
							</layoutData>
						</Button>
						<Button width="100%" text="hello world" >
							<layoutData>
								<layout:SplitterLayoutData size="auto" resizable="false"/>
							</layoutData>
						</Button>
						<Button width="100%" text="hello world" >
							<layoutData>
								<layout:SplitterLayoutData size="auto"/>
							</layoutData>
						</Button>
					</layout:Splitter>
				</Page>
			</pages>
		</App>
	</Shell>
</mvc:View>
